setup.py
collective/__init__.py
collective.validator.xhtmlStrict.egg-info/PKG-INFO
collective.validator.xhtmlStrict.egg-info/SOURCES.txt
collective.validator.xhtmlStrict.egg-info/dependency_links.txt
collective.validator.xhtmlStrict.egg-info/entry_points.txt
collective.validator.xhtmlStrict.egg-info/namespace_packages.txt
collective.validator.xhtmlStrict.egg-info/not-zip-safe
collective.validator.xhtmlStrict.egg-info/requires.txt
collective.validator.xhtmlStrict.egg-info/top_level.txt
collective/validator/__init__.py
collective/validator/xhtmlStrict/HISTORY.txt
collective/validator/xhtmlStrict/README.txt
collective/validator/xhtmlStrict/__init__.py
collective/validator/xhtmlStrict/adapter.py
collective/validator/xhtmlStrict/config.py
collective/validator/xhtmlStrict/configure.zcml
collective/validator/xhtmlStrict/refresh.txt
collective/validator/xhtmlStrict/version.txt
collective/validator/xhtmlStrict/i18n/collective.validator.xhtmlStrict-it.po
collective/validator/xhtmlStrict/interfaces/__init__.py
collective/validator/xhtmlStrict/interfaces/interfaces.py
collective/validator/xhtmlStrict/tests/__init__.py
collective/validator/xhtmlStrict/tests/test_plone_validation.py