Metadata-Version: 1.0
Name: collective.validator.xhtmlStrict
Version: 1.2.0
Summary: XHTML Strict Validator for collective.validator.base
Home-page: https://svn.plone.org/svn/collective/collective.validator.xhtmlStrict
Author: Andrea Cecchi
Author-email: sviluppoplone@redturtle.net
License: GPL
Keywords: Plone Validator XHTMLStrict
Platform: UNKNOWN
Classifier: Framework :: Plone
Classifier: Framework :: Zope2
Classifier: Framework :: Zope3
Classifier: Programming Language :: Python
Classifier: Topic :: Software Development :: Libraries :: Python Modules
